nnts/__init__.py
nnts/data/__init__.py
nnts/data/monash.json
nnts/data/tsf.py
nnts/datasets.py
nnts/events.py
nnts/lags.py
nnts/loggers.py
nnts/metrics.py
nnts/plotting.py
nnts/preprocessing.py
nnts/torch/__init__.py
nnts/torch/datasets.py
nnts/torch/models/__init__.py
nnts/torch/models/autoformer.py
nnts/torch/models/baselstm.py
nnts/torch/models/deepar.py
nnts/torch/models/dlinear.py
nnts/torch/models/itransformer.py
nnts/torch/models/nbeats.py
nnts/torch/models/nhits.py
nnts/torch/models/nlinear.py
nnts/torch/models/patchtsmixer.py
nnts/torch/models/patchtst.py
nnts/torch/models/seglstm.py
nnts/torch/models/tide.py
nnts/torch/models/timemixer.py
nnts/torch/models/timesnet.py
nnts/torch/models/tsmixer.py
nnts/torch/models/unrolledlstm.py
nnts/torch/preprocessing.py
nnts/torch/trainers.py
nnts/torch/utils.py
nnts/trainers.py
nnts/utils.py
nnts-0.1.5.dist-info/LICENSE
nnts-0.1.5.dist-info/METADATA
nnts-0.1.5.dist-info/WHEEL
nnts-0.1.5.dist-info/RECORD
